jirap/__init__.py
jirap-0.0.5.dist-info/LICENSE
jirap-0.0.5.dist-info/METADATA
jirap-0.0.5.dist-info/WHEEL
jirap-0.0.5.dist-info/top_level.txt
jirap-0.0.5.dist-info/RECORD
