Metadata-Version: 2.1
Name: jirap
Version: 0.0.5
Summary: A small example package
Home-page: https://github.com/xafardero/jirap
Author: Xavier Mabras
Author-email: xavier.mabras@protonmail.ch
License: UNKNOWN
Platform: UNKNOWN
Classifier: Programming Language :: Python :: 3
Classifier: License :: OSI Approved :: MIT License
Classifier: Operating System :: OS Independent
Requires-Dist: jira
